hurpetools/__init__.py
hurpetools/hurpetools.py
hurpetools-0.0.3.dist-info/LICENSE
hurpetools-0.0.3.dist-info/METADATA
hurpetools-0.0.3.dist-info/WHEEL
hurpetools-0.0.3.dist-info/top_level.txt
hurpetools-0.0.3.dist-info/RECORD
