Metadata-Version: 2.1
Name: hurpetools
Version: 0.0.3
Summary: close ssl verify and ignore warning
Home-page: https://github.com/BigDataFounder/string2date
Author: hurpe
Author-email: hurpe.ma@gmail.com
License: MIT
Platform: UNKNOWN
License-File: LICENSE
